pyams_portal/__init__.py
pyams_portal/include.py
pyams_portal/interfaces.py
pyams_portal/page.py
pyams_portal/portlet.py
pyams_portal/slot.py
pyams_portal/template.py
pyams_portal/thumbnails.py
pyams_portal/utils.py
pyams_portal/doctests/README.rst
pyams_portal/generations/__init__.py
pyams_portal/generations/evolve1.py
pyams_portal/generations/evolve2.py
pyams_portal/generations/evolve3.py
pyams_portal/generations/evolve4.py
pyams_portal/locales/pyams_portal.pot
pyams_portal/locales/fr/LC_MESSAGES/pyams_portal.mo
pyams_portal/locales/fr/LC_MESSAGES/pyams_portal.po
pyams_portal/portlets/__init__.py
pyams_portal/portlets/cards/__init__.py
pyams_portal/portlets/cards/interfaces.py
pyams_portal/portlets/cards/skin/__init__.py
pyams_portal/portlets/cards/skin/interfaces.py
pyams_portal/portlets/cards/skin/templates/cards-masonry.pt
pyams_portal/portlets/cards/skin/templates/cards.pt
pyams_portal/portlets/cards/zmi/__init__.py
pyams_portal/portlets/cards/zmi/templates/cards-preview.pt
pyams_portal/portlets/carousel/__init__.py
pyams_portal/portlets/carousel/interfaces.py
pyams_portal/portlets/carousel/skin/__init__.py
pyams_portal/portlets/carousel/skin/interfaces.py
pyams_portal/portlets/carousel/skin/templates/carousel.pt
pyams_portal/portlets/carousel/zmi/__init__.py
pyams_portal/portlets/carousel/zmi/templates/carousel-preview.pt
pyams_portal/portlets/html/__init__.py
pyams_portal/portlets/html/interfaces.py
pyams_portal/portlets/html/skin/__init__.py
pyams_portal/portlets/html/skin/interfaces.py
pyams_portal/portlets/html/skin/templates/html-alert.pt
pyams_portal/portlets/html/skin/templates/html.pt
pyams_portal/portlets/html/skin/templates/raw-code.pt
pyams_portal/portlets/html/skin/templates/raw.pt
pyams_portal/portlets/html/zmi/__init__.py
pyams_portal/portlets/html/zmi/templates/html-preview.pt
pyams_portal/portlets/html/zmi/templates/raw-preview.pt
pyams_portal/portlets/image/__init__.py
pyams_portal/portlets/image/interfaces.py
pyams_portal-2.6.2.dist-info/LICENSE
pyams_portal-2.6.2.dist-info/METADATA
pyams_portal-2.6.2.dist-info/WHEEL
pyams_portal-2.6.2.dist-info/entry_points.txt
pyams_portal-2.6.2.dist-info/namespace_packages.txt
pyams_portal-2.6.2.dist-info/top_level.txt
pyams_portal-2.6.2.dist-info/RECORD
