Metadata-Version: 2.1
Name: pyams-portal
Version: 2.6.2
Summary: PyAMS portlets management package
Home-page: https://pyams.readthedocs.io
Author: Thierry Florac
Author-email: tflorac@ulthar.net
License: ZPL
Keywords: Pyramid PyAMS
Classifier: License :: OSI Approved :: Zope Public License
Classifier: Development Status :: 4 - Beta
Classifier: Programming Language :: Python
Classifier: Framework :: Pyramid
Classifier: Topic :: Software Development :: Libraries :: Python Modules
License-File: LICENSE
Requires-Dist: setuptools
Requires-Dist: persistent
Requires-Dist: pyams-file
Requires-Dist: pyams-i18n
Requires-Dist: pyams-layer
Requires-Dist: pyams-pagelet
Requires-Dist: pyams-security
Requires-Dist: pyams-sequence
Requires-Dist: pyams-site
Requires-Dist: pyams-skin >2.1.0
Requires-Dist: pyams-template
Requires-Dist: pyams-utils >=2.2.0
Requires-Dist: pyams-workflow
Requires-Dist: pyramid >=2.0.0
Requires-Dist: venusian
Requires-Dist: zope.annotation
Requires-Dist: zope.container
Requires-Dist: zope.contentprovider
Requires-Dist: zope.copy
Requires-Dist: zope.interface
Requires-Dist: zope.lifecycleevent
Requires-Dist: zope.location
Requires-Dist: zope.schema
Requires-Dist: zope.traversing
Provides-Extra: test
Requires-Dist: pyams-catalog ; extra == 'test'
Requires-Dist: pyams-form ; extra == 'test'
Requires-Dist: pyams-zmi ; extra == 'test'
Requires-Dist: pyramid-zcml ; extra == 'test'
Requires-Dist: zope.exceptions ; extra == 'test'
